README.rst
setup.py
easycommandline/__init__.py
easycommandline/easycommandline.py
easycommandline/terminalstyle.py
easycommandline.egg-info/PKG-INFO
easycommandline.egg-info/SOURCES.txt
easycommandline.egg-info/dependency_links.txt
easycommandline.egg-info/top_level.txt
easycommandline.egg-info/zip-safe