Metadata-Version: 1.1
Name: easycommandline
Version: 1.8.1
Summary: python command-line interfaces made easy
Home-page: https://github.com/tracycool/easycommandline
Author: Tracy Lai
Author-email: me@tracycool.com
License: MIT
Keywords: python command line option argument argv
Platform: UNKNOWN
Classifier: License :: OSI Approved :: MIT License
Classifier: Programming Language :: Python
Classifier: Intended Audience :: Developers
Classifier: Operating System :: OS Independent
